poetry_test_6/__init__.py
poetry_test_6-0.1.0.dist-info/WHEEL
poetry_test_6-0.1.0.dist-info/METADATA
poetry_test_6-0.1.0.dist-info/RECORD
