Metadata-Version: 2.1
Name: poetry-test-6
Version: 0.1.0
Summary: 
Author: Peter Lin
Author-email: Peter.Lin@nike.com
Requires-Python: >=2.7,<3.0
Classifier: Programming Language :: Python :: 2
Classifier: Programming Language :: Python :: 2.7
Requires-Dist: pendulum (>=2.1.0,<3.0.0)
